easy_time_tracker/__init__.py
easy_time_tracker/cli.py
easy_time_tracker/constants.py
easy_time_tracker/easy_time_tracker.py
easy_time_tracker/gui.py
easy_time_tracker/version.py
easy_time_tracker/util/__init__.py
easy_time_tracker/util/file_read_write.py
easy_time_tracker/util/schemas.py
easy_time_tracker-1.0.2.dist-info/LICENSE
easy_time_tracker-1.0.2.dist-info/METADATA
easy_time_tracker-1.0.2.dist-info/WHEEL
easy_time_tracker-1.0.2.dist-info/entry_points.txt
easy_time_tracker-1.0.2.dist-info/top_level.txt
easy_time_tracker-1.0.2.dist-info/RECORD
