Metadata-Version: 2.1
Name: easy-time-tracker
Version: 1.0.2
Summary: A simple time tracking tool
Home-page: https://easy-time-tracker.readthedocs.io
Author: Benjamin P. Trachtenberg
Author-email: e_ben_75-python@yahoo.com
License: The MIT License (MIT)
Project-URL: Documentation, https://easy-time-tracker.readthedocs.io/en/latest/
Project-URL: Source, https://github.com/btr1975/easy-time-tracker
Project-URL: Tracker, https://github.com/btr1975/easy-time-tracker/issues
Platform: UNKNOWN
Classifier: Development Status :: 5 - Production/Stable
Classifier: License :: OSI Approved :: MIT License
Classifier: Intended Audience :: Developers
Classifier: Natural Language :: English
Classifier: Operating System :: MacOS :: MacOS X
Classifier: Operating System :: POSIX
Classifier: Operating System :: POSIX :: BSD
Classifier: Operating System :: POSIX :: Linux
Classifier: Operating System :: Microsoft :: Windows
Classifier: Programming Language :: Python :: 3
Classifier: Programming Language :: Python :: 3 :: Only
Classifier: Programming Language :: Python :: 3.6
Classifier: Programming Language :: Python :: 3.7
Classifier: Programming Language :: Python :: 3.8
Classifier: Programming Language :: Python :: 3.9
Classifier: Programming Language :: Python :: 3.10
Requires-Python: >=3.6
License-File: LICENSE
Requires-Dist: pydantic (~=1.9.0)
Requires-Dist: openpyxl (~=3.0.9)
Requires-Dist: pandas (~=1.1.5) ; python_version == "3.6"
Requires-Dist: pandas (~=1.3.5) ; python_version == "3.7"
Requires-Dist: pandas (~=1.4.0) ; python_version >= "3.8"
